aoc_cli/__init__.py
aoc_cli/__main__.py
aoc_cli/utils.py
aoc_cli/validations.py
aoc_cli-0.0.8.dist-info/LICENSE
aoc_cli-0.0.8.dist-info/METADATA
aoc_cli-0.0.8.dist-info/WHEEL
aoc_cli-0.0.8.dist-info/entry_points.txt
aoc_cli-0.0.8.dist-info/top_level.txt
aoc_cli-0.0.8.dist-info/RECORD
