Metadata-Version: 2.1
Name: aoc-cli
Version: 0.0.8
Summary: Advent of Code scaffolding CLI
Author-email: Emil Kloeden <emilkloeden@gmail.com>
Project-URL: Homepage, https://github.com/emilkloeden/aoc-cli
Project-URL: Bug Tracker, https://github.com/emilkloeden/aoc-cli/issues
Classifier: Programming Language :: Python :: 3
Classifier: License :: OSI Approved :: MIT License
Classifier: Operating System :: OS Independent
Requires-Python: >=3.10
License-File: LICENSE
Requires-Dist: python-dotenv (==0.21.0)
Requires-Dist: aoc-cli-python (>=0.0.4)
